boa/__init__.py
boa/coverage.py
boa/dealer.py
boa/debugger.py
boa/deployments.py
boa/environment.py
boa/explorer.py
boa/interpret.py
boa/ipython.py
boa/network.py
boa/precompile.py
boa/profiling.py
boa/rpc.py
boa/verifiers.py
boa/contracts/__init__.py
boa/contracts/base_evm_contract.py
boa/contracts/call_trace.py
boa/contracts/event_decoder.py
boa/contracts/trace-template.html
boa/contracts/abi/__init__.py
boa/contracts/abi/abi_contract.py
boa/contracts/vvm/__init__.py
boa/contracts/vvm/vvm_contract.py
boa/contracts/vyper/__init__.py
boa/contracts/vyper/ast_utils.py
boa/contracts/vyper/compiler_utils.py
boa/contracts/vyper/decoder_utils.py
boa/contracts/vyper/ir_executor.py
boa/contracts/vyper/vyper_contract.py
boa/integrations/__init__.py
boa/integrations/jupyter/__init__.py
boa/integrations/jupyter/browser.py
boa/integrations/jupyter/constants.py
boa/integrations/jupyter/handlers.py
boa/integrations/jupyter/jupyter.js
boa/test/__init__.py
boa/test/plugin.py
boa/test/strategies.py
boa/util/abi.py
boa/util/disk_cache.py
boa/util/eip1167.py
boa/util/eip5202.py
boa/util/evm.py
boa/util/exceptions.py
boa/util/lrudict.py
boa/util/open_ctx.py
boa/util/sqlitedb.py
boa/vm/fast_accountdb.py
boa/vm/fast_mem.py
boa/vm/fork.py
boa/vm/gas_meters.py
boa/vm/py_evm.py
boa/vm/utils.py
titanoboa-0.2.7.dist-info/licenses/LICENSE
titanoboa-0.2.7.dist-info/METADATA
titanoboa-0.2.7.dist-info/WHEEL
titanoboa-0.2.7.dist-info/entry_points.txt
titanoboa-0.2.7.dist-info/top_level.txt
titanoboa-0.2.7.dist-info/RECORD
