Metadata-Version: 2.4
Name: titanoboa
Version: 0.2.7
Summary: A Vyper interpreter
License: Copyright 2022 Charles Cooper
Keywords: ethereum,evm,smart contract,development
Classifier: Topic :: Software Development
License-File: LICENSE
Requires-Dist: vyper>=0.4.2
Requires-Dist: eth-stdlib<0.3.0,>=0.2.7
Requires-Dist: eth-abi
Requires-Dist: py-evm>=0.10.0b4
Requires-Dist: eth-typing
Requires-Dist: hypothesis
Requires-Dist: pytest
Requires-Dist: pytest-cov
Requires-Dist: vvm>=0.3.2
Requires-Dist: typing-extensions
Requires-Dist: rich
Requires-Dist: requests
Requires-Dist: eth-account>=0.13.0
Requires-Dist: mkdocs-material==9.5.41
Provides-Extra: forking-recommended
Requires-Dist: ujson>=5.10.0; extra == "forking-recommended"
Requires-Dist: requests-cache>=1.2.1; extra == "forking-recommended"
Provides-Extra: colab
Requires-Dist: ipykernel>=6.29.4; extra == "colab"
Dynamic: license-file
